{
  "id": "3f5fee99-5206-4938-9171-5d53b30f4846",
  "slug": "aws-s3",
  "title": "AWS S3",
  "iconSlug": "amazons3",
  "iconColor": null,
  "description": null,
  "category": [
    "Infra"
  ],
  "proficiency": "1. 초보",
  "visible": true,
  "parentSkills": [],
  "childSkills": [],
  "relatedSkills": [],
  "usedInProjects": [
    "3c9f2d34-a501-46a5-b644-43a316904b1e",
    "4b1c905e-56cf-4bc8-915d-c768337edf4e"
  ],
  "usedAsLanguage": [],
  "usageCount": 2,
  "iconUrl": "./assets/s3-MxNDkud2VicA.webp",
  "iconEmoji": null,
  "coverUrl": null,
  "projectsUsingAsSkill": [
    "eyevacs4",
    "아이박스-주차"
  ],
  "projectsUsingAsLanguage": []
}
