{
  "id": "34b307a0-5ef9-46dd-8ef3-b3b83de63890",
  "slug": "gcp",
  "title": "GCP",
  "iconSlug": "googlecloud",
  "iconColor": null,
  "description": null,
  "category": [
    "Infra"
  ],
  "proficiency": "2. 중급",
  "visible": false,
  "parentSkills": [],
  "childSkills": [],
  "relatedSkills": [],
  "usedInProjects": [
    "8fda43a6-b6cb-495f-8256-898cd2e66b03",
    "f0499ae1-e215-4aaf-8066-fcd9428be8c8",
    "10722f86-9794-4ec2-bb11-5b92a16970e5",
    "0371c463-7d0e-4c0b-8b61-f546160c9982",
    "1341a9fd-f7bb-43ed-81c3-07ae0ff07d07"
  ],
  "usedAsLanguage": [],
  "usageCount": 5,
  "iconUrl": "./assets/s3-iL2djcC5zdmc.svg",
  "iconEmoji": null,
  "coverUrl": null,
  "projectsUsingAsSkill": [
    "canetis",
    "smart-home-with-google-home",
    "smart-pot",
    "stella",
    "비탈길-vitalgheal"
  ],
  "projectsUsingAsLanguage": []
}
