{
  "id": "7ec0d0fe-35e0-4a2d-9092-56aef0832ab8",
  "slug": "figma",
  "title": "Figma",
  "iconSlug": "figma",
  "iconColor": null,
  "description": null,
  "category": [
    "협업/문서",
    "디자인"
  ],
  "proficiency": "2. 중급",
  "visible": true,
  "parentSkills": [],
  "childSkills": [],
  "relatedSkills": [],
  "usedInProjects": [
    "f8408212-01e1-4ca5-ae9b-0aff52122cff",
    "4b1c905e-56cf-4bc8-915d-c768337edf4e",
    "be36aef1-f29e-4071-bfd4-fa64bbb6f453"
  ],
  "usedAsLanguage": [],
  "usageCount": 3,
  "iconUrl": "./assets/s3-L0ljb24uc3Zn.svg",
  "iconEmoji": null,
  "coverUrl": null,
  "projectsUsingAsSkill": [
    "alpaconnect",
    "eyevacs4",
    "wrtn-magic"
  ],
  "projectsUsingAsLanguage": []
}
